<?xml version='1.0' encoding='utf-8' standalone='yes'?>
<song>
  <meta>
    <id>10977</id>
    <date>
      <year-start>1605</year-start>
      <year-end>1605</year-end>
    </date>
    <location>
      <orginal-name>amsterdam</orginal-name>
      <standard-name>Amsterdam, The Netherlands</standard-name>
      <coordinates>
        <lon>52.3745403</lon>
        <lat>4.89797550561798</lat>
      </coordinates>
    </location>
    <tags>
      <tag standard-name="liefdeslied" translation="love song">liefdeslied</tag>
    </tags>
    <melody>Venus gij en uw kind</melody>
    <categories>
      <category translation="love and sex">liefde en seks</category>
    </categories>
  <author>Anonymous</author></meta>
  <text>
    <lg type="song">
      <lg id="s1" type="stanza">
        <l id="s1:l1" met="3" type="-+">Venus ghy end' u <rhyme label="a" type="m">kindt</rhyme></l>
        <l id="s1:l2" met="3" type="-+">Zijt alle beyde <rhyme label="a" type="m" corresp="#s1:l1">blindt</rhyme></l>
        <l id="s1:l3" met="3" type="-+">En doet oock heel <rhyme label="b" type="f">verblenden</rhyme></l>
        <l id="s1:l4" met="3" type="-+">die haer tot u gaen <rhyme label="b" type="f" corresp="#s1:l3">wenden</rhyme></l>
        <l id="s1:l5" met="6" type="-+">dit heb ick wel ervaren // in myne jonge <rhyme label="c" type="f">Iaren</rhyme>.</l>
      </lg>
      <lg id="s2" type="stanza">
        <l id="s2:l1" met="3" type="-+">Cupido vlieght seer <rhyme label="a" type="m">licht</rhyme></l>
        <l id="s2:l2" met="3" type="-+">doorwont haest met zijn <rhyme label="a" type="m" corresp="#s2:l1">schicht</rhyme>,</l>
        <l id="s2:l3" met="3" type="-+">So wat hy eens <rhyme label="b" type="f">aenricht</rhyme></l>
        <l id="s2:l4" met="3" type="-+">Het hart terstont <rhyme label="b" type="f" corresp="#s2:l3">vervoert</rhyme>,</l>
        <l id="s2:l5" met="6" type="-+">dat heb ic wel <rhyme label="c" type="f">ervaren</rhyme>//</l>
      </lg>
      <lg id="s3" type="stanza">
        <l id="s3:l1" met="3" type="-+">Door eens vrolijck te <rhyme label="a" type="m">zijn</rhyme></l>
        <l id="s3:l2" met="3" type="-+">Gheeft ghy veel duysent <rhyme label="a" type="m" corresp="#s3:l1">pijn</rhyme></l>
        <l id="s3:l3" met="3" type="-+">Door eenmael te <rhyme label="b" type="f">verblijden</rhyme></l>
        <l id="s3:l4" met="3" type="-+">Gheeft ghy hartseer en <rhyme label="b" type="f" corresp="#s3:l3">lijden</rhyme>,</l>
        <l id="s3:l5" met="6" type="-+">dit heb ick wel ervaren // in mijne jonge <rhyme label="c" type="f">Iaren</rhyme>.</l>
      </lg>
      <lg id="s4" type="stanza">
        <l id="s4:l1" met="3" type="-+">Dies Princen is mijn <rhyme label="a" type="m">aert</rhyme>.</l>
        <l id="s4:l2" met="3" type="-+">de liefde haest <rhyme label="a" type="m" corresp="#s4:l1">verlaet</rhyme></l>
        <l id="s4:l3" met="3" type="-+">Ghy sulter niet in <rhyme label="b" type="f">vynen</rhyme></l>
        <l id="s4:l4" met="3" type="-+">Dan door druck te <rhyme label="b" type="f" corresp="#s4:l3">verdwynen</rhyme>,</l>
        <l id="s4:l5" met="6" type="-+">Dit heb ick wel ervaren // in myne jonghe <rhyme label="c" type="f">Iaren</rhyme>.</l>
      </lg>
    </lg>
  </text>
</song>
