<?xml version='1.0' encoding='utf-8' standalone='yes'?>
<song>
  <meta>
    <id>115957</id>
    <date>
      <year-start>1649</year-start>
      <year-end>1649</year-end>
    </date>
    <location>
      <orginal-name>utrecht</orginal-name>
      <standard-name>Utrecht, The Netherlands</standard-name>
      <coordinates>
        <lon>52.0949753</lon>
        <lat>5.109708</lat>
      </coordinates>
    </location>
    <tags>
      <tag standard-name="bijbels historielied" translation="biblical history song">bijbels historielied</tag>
    </tags>
    <melody>O kerstnacht schoner dan de dagen</melody>
    <categories>
      <category translation="religion">godsdienst</category>
    </categories>
  <author>Anonymous</author></meta>
  <text>
    <lg type="song">
      <lg id="s1" type="stanza">
        <l id="s1:l1">WAt meught ghy dert'le Ionghelinghen</l>
        <l id="s1:l2">Van Faëton en Orpheus singhen,</l>
        <l id="s1:l3">En Poliphemus aen de strandt,</l>
        <l id="s1:l4">Van Daphne die Phoebus nae jaeghden,</l>
        <l id="s1:l5">Verandert in een Boom, en klaeghden</l>
        <l id="s1:l6">Van Apols geyle Minne-brandt.</l>
      </lg>
      <lg id="s2" type="stanza">
        <l id="s2:l1">Dit sijn al Fabelrijcke droomen,</l>
        <l id="s2:l2">Die van de Heydens zijn gekomen:</l>
        <l id="s2:l3">Denckt dat u noodigh is een dingh,</l>
        <l id="s2:l4">Wilt ghy in Godt u hart verlichten,</l>
        <l id="s2:l5">Singht of leest stichtelijcke Dichten,</l>
        <l id="s2:l6">Al van Loths Wijfs veranderingh.</l>
      </lg>
      <lg id="s3" type="stanza">
        <l id="s3:l1">Singht hoe uyt Sodom' geleydt wieren</l>
        <l id="s3:l2">Loth, Vrouw, en twee Dochters, haer vieren,</l>
        <l id="s3:l3">En hoe haer d'Heer verboden hadt</l>
        <l id="s3:l4">Niet om te kijcken, maer al gaende</l>
        <l id="s3:l5">Bleef Loths Wijf in een Zout-steen staende,</l>
        <l id="s3:l6">Dees vr'anderingh mensch gedenckt dat.</l>
      </lg>
      <lg id="s4" type="stanza">
        <l id="s4:l1">Leert hier uyt Godts gebodt om 't houwen,</l>
        <l id="s4:l2">Oock na te komen, en te schouwen</l>
        <l id="s4:l3">Al 't geen de arme ziele schaedt:</l>
        <l id="s4:l4">Wilt nae 't vergancklijck niet om kijcken,</l>
        <l id="s4:l5">Wilt ghy behouden en verrijcken,</l>
        <l id="s4:l6">Elck siet wel toe dat hy vast staet.</l>
      </lg>
      <lg id="s5" type="stanza">
        <l id="s5:l1">Wilt u aen 't Aerdtsch so niet vergapen,</l>
        <l id="s5:l2">Ghy die roemt te zijn Christi Schapen,</l>
        <l id="s5:l3">Kijckt niet te rugh, als Loths Vrouw dee:</l>
        <l id="s5:l4">Laet u de werelt niet verleyden,</l>
        <l id="s5:l5">Maer wilt uyt 't zondigh Sodom' scheyden,</l>
        <l id="s5:l6">En gaet recht deur na Ninive.</l>
      </lg>
    </lg>
  </text>
</song>
