<?xml version='1.0' encoding='utf-8' standalone='yes'?>
<song>
  <meta>
    <id>117929</id>
    <date>
      <year-start>1720</year-start>
      <year-end>1720</year-end>
    </date>
    <location>
      <orginal-name>leiden</orginal-name>
      <standard-name>Leiden, The Netherlands</standard-name>
      <coordinates>
        <lon>52.1598645</lon>
        <lat>4.4824271</lat>
      </coordinates>
    </location>
    <tags>
      <tag standard-name="bespiegelend lied" translation="reflective song">bespiegelend lied</tag>
    </tags>
    <melody>Réveillez-vous belle endormie</melody>
    <categories>
      <category translation="religion">godsdienst</category>
    </categories>
  <author>Carolus Tuinman</author></meta>
  <text>
    <lg type="song">
      <lg id="s1" type="stanza">
        <l id="s1:l1">'t Is goed een goeden raad te vinden,</l>
        <l id="s1:l2">Maar 't komt op 't uit te voeren aan.</l>
        <l id="s1:l3">Wie zal de kat de bel aanbinden?</l>
        <l id="s1:l4">Wat muizen zullen dat bestaan?</l>
      </lg>
      <lg id="s2" type="stanza">
        <l id="s2:l1">Wat konnen zulke raaden baaten,</l>
        <l id="s2:l2">Hoe wys, hoe wel beraamt in schyn,</l>
        <l id="s2:l3">Als men die onverzocht moet laten:</l>
        <l id="s2:l4">Wyl niemand durft de daader zyn.</l>
      </lg>
      <lg id="s3" type="stanza">
        <l id="s3:l1">Gy weet wel midd'len voor te dragen:</l>
        <l id="s3:l2">Maar schuift den last op 's naasten bult,</l>
        <l id="s3:l3">En wilt uw' huid daar niet aan wagen.</l>
        <l id="s3:l4">Mislukt het, 't zal zyn 's anders schuld.</l>
      </lg>
      <lg id="s4" type="stanza">
        <l id="s4:l1">Gy woud van ver wel staan bekyken,</l>
        <l id="s4:l2">Wat uitslag doch uw raad genoot;</l>
        <l id="s4:l3">Mits dat gy 't onweêr kont ontwyken,</l>
        <l id="s4:l4">En veilig blyven buiten schoot.</l>
      </lg>
      <lg id="s5" type="stanza">
        <l id="s5:l1">Hoor raader, mag ik ook eens raaden,</l>
        <l id="s5:l2">Ik raade, dat gy voor moogt gaan,</l>
        <l id="s5:l3">Om aan te wyzen zulke paden,</l>
        <l id="s5:l4">Als gy wilt and'ren in doen slaan.</l>
      </lg>
    </lg>
  </text>
</song>
