<?xml version='1.0' encoding='utf-8' standalone='yes'?>
<song>
  <meta>
    <id>1372</id>
    <date>
      <year-start>1613</year-start>
      <year-end>1613</year-end>
    </date>
    <location>
      <orginal-name>amsterdam?</orginal-name>
      <standard-name>Amsterdam, The Netherlands</standard-name>
      <coordinates>
        <lon>52.3745403</lon>
        <lat>4.89797550561798</lat>
      </coordinates>
    </location>
    <tags/>
    <melody>Een ridder en een meisje jong</melody>
  <author>Anonymous</author></meta>
  <text>
    <lg type="song">
      <lg id="s1" type="stanza">
        <l id="s1:l1" met="4" type="-+">EEn Ridder en een Meysken <rhyme label="a" type="m">jonck</rhyme></l>
        <l id="s1:l2" met="3" type="-+">Op een Revierken dat sy <rhyme label="b" type="f">saten</rhyme>,</l>
        <l id="s1:l3" met="4" type="-+">Hoe stille dat het water <rhyme label="c" type="m">stondt</rhyme></l>
        <l id="s1:l4" met="3" type="-+">Als sy van goeder minnen <rhyme label="b" type="f" corresp="#s1:l2">spraken</rhyme>.</l>
      </lg>
      <lg id="s2" type="stanza">
        <l id="s2:l1" met="4" type="-+">Och seght my stout Ridder <rhyme label="a" type="m">goet</rhyme></l>
        <l id="s2:l2" met="3" type="-+">Ick soude soo gaerne <rhyme label="b" type="f">weten</rhyme>,</l>
        <l id="s2:l3" met="4" type="-+">Waerom dattet Water soo stille <rhyme label="c" type="m">staet</rhyme></l>
        <l id="s2:l4" met="3" type="-+">Als wy van goeder minnen <rhyme label="b" type="f" corresp="#s2:l2">spreken</rhyme>.</l>
      </lg>
      <lg id="s3" type="stanza">
        <l id="s3:l1" met="4" type="-+">Dattet Water soo stille <rhyme label="a" type="m">staet</rhyme></l>
        <l id="s3:l2" met="3" type="-+">Dat en gheeft my jae gheen <rhyme label="b" type="f">vreemde</rhyme>,</l>
        <l id="s3:l3" met="4" type="-+">Ick hebbe soo menighe jonghe <rhyme label="c" type="m">Maecht</rhyme></l>
        <l id="s3:l4" met="3" type="-+">Ghebrocht in swaer <rhyme label="b" type="f" corresp="#s3:l2">ellende</rhyme>.</l>
      </lg>
      <lg id="s4" type="stanza">
        <l id="s4:l1" met="4" type="-+">Hebdy soo menighen jonghe <rhyme label="a" type="m">Maecht</rhyme></l>
        <l id="s4:l2" met="3" type="-+">Ghebrocht in swaer <rhyme label="b" type="f">ellende</rhyme>,</l>
        <l id="s4:l3" met="4" type="-+">Wacht u, wacht u, stout Ridder <rhyme label="c" type="m">goet</rhyme></l>
        <l id="s4:l4" met="3" type="-+">Dat u God niet en <rhyme label="b" type="f" corresp="#s4:l2">schende</rhyme>.</l>
      </lg>
      <lg id="s5" type="stanza">
        <l id="s5:l1" met="4" type="-+">Ick weet noch een soo hooghen <rhyme label="a" type="m">Bergh</rhyme></l>
        <l id="s5:l2" met="3" type="-+">Boven alle Berghen is hy <rhyme label="b" type="f">hooghe</rhyme>,</l>
        <l id="s5:l3" met="4" type="-+">Die sal ick noch in dalen <rhyme label="c" type="m">brenghen</rhyme></l>
        <l id="s5:l4" met="3" type="-+">Daerom is dat ick <rhyme label="b" type="f" corresp="#s5:l2">pooge</rhyme>.</l>
      </lg>
      <lg id="s6" type="stanza">
        <l id="s6:l1" met="4" type="-+">Suldy mijn Vaders hooghen <rhyme label="a" type="m">Bergh</rhyme></l>
        <l id="s6:l2" met="3" type="-+">Tot eenen dale <rhyme label="b" type="f">brenghen</rhyme>,</l>
        <l id="s6:l3" met="4" type="-+">Ick saghe u veel liever stout Ridder <rhyme label="c" type="m">goet</rhyme></l>
        <l id="s6:l4" met="3" type="-+">By uwer Keelen <rhyme label="b" type="f" corresp="#s6:l2">hanghen</rhyme>.</l>
      </lg>
      <lg id="s7" type="stanza">
        <l id="s7:l1" met="4" type="-+">Ick hadde noch veel <rhyme label="a" type="m">liever</rhyme></l>
        <l id="s7:l2" met="3" type="-+">Dat u die Sonne <rhyme label="b" type="f">beschene</rhyme></l>
        <l id="s7:l3" met="4" type="-+">Al onder 'thol van uwen <rhyme label="c" type="m">voeten</rhyme></l>
        <l id="s7:l4" met="3" type="-+">Den bast al om u <rhyme label="b" type="f" corresp="#s7:l2">keele</rhyme>.</l>
      </lg>
      <lg id="s8" type="stanza">
        <l id="s8:l1" met="4" type="-+">Dat meysken was jonck ende daer toe <rhyme label="a" type="m">dom</rhyme></l>
        <l id="s8:l2" met="3" type="-+">Zy en wist niet wat sy <rhyme label="b" type="f">seyde</rhyme>,</l>
        <l id="s8:l3" met="4" type="-+">Doen sy in haer Liefs armen <rhyme label="c" type="m">lach</rhyme>,</l>
        <l id="s8:l4" met="3" type="-+">Doen was den Berch ter <rhyme label="b" type="f" corresp="#s8:l2">neder</rhyme>.</l>
      </lg>
      <lg id="s9" type="stanza">
        <l id="s9:l1" met="4" type="-+">Och seght my soet Meysken <rhyme label="a" type="m">jonck</rhyme></l>
        <l id="s9:l2" met="3" type="-+">Is nu mijn Keele <rhyme label="b" type="f">ghehangen</rhyme>,</l>
        <l id="s9:l3" met="4" type="-+">Nu is ws Vaders hooghen <rhyme label="c" type="m">Bergh</rhyme>,</l>
        <l id="s9:l4" met="3" type="-+">In eenen dale <rhyme label="b" type="f" corresp="#s9:l2">verganghen</rhyme>.</l>
      </lg>
      <lg id="s10" type="stanza">
        <l id="s10:l1" met="4" type="-+">Och doen dat Meysken gewaer <rhyme label="a" type="m">wert</rhyme></l>
        <l id="s10:l2" met="3" type="-+">Dat sy een Kindeken bleef <rhyme label="b" type="f">draghen</rhyme>,</l>
        <l id="s10:l3" met="4" type="-+">Zy ginck al voor den Ridder <rhyme label="c" type="m">staen</rhyme></l>
        <l id="s10:l4" met="3" type="-+">Zy badt al om <rhyme label="b" type="f" corresp="#s10:l2">ghenade</rhyme>.</l>
      </lg>
      <lg id="s11" type="stanza">
        <l id="s11:l1" met="4" type="-+">Genade sprack sy stout Ridder <rhyme label="a" type="m">fijn</rhyme></l>
        <l id="s11:l2" met="3" type="-+">Ghenade mijnen <rhyme label="b" type="f">lijve</rhyme>,</l>
        <l id="s11:l3" met="4" type="-+">Ick was een goet <rhyme label="c" type="m">Maechdekijn</rhyme></l>
        <l id="s11:l4" met="3" type="-+">Nu moet ick met uwen Kinde <rhyme label="b" type="f" corresp="#s11:l2">blyven</rhyme>.</l>
      </lg>
      <lg id="s12" type="stanza">
        <l id="s12:l1" met="4" type="-+">Wat ghenade soude ick u <rhyme label="a" type="m">doen</rhyme></l>
        <l id="s12:l2" met="3" type="-+">Ghy zijt geen <rhyme label="b" type="f">Keyserinne</rhyme>,</l>
        <l id="s12:l3" met="4" type="-+">Ick mocht u mijn Schiltknecht <rhyme label="c" type="m">gheven</rhyme></l>
        <l id="s12:l4" met="3" type="-+">Kost ick hem daer toe <rhyme label="b" type="f" corresp="#s12:l2">brenghen</rhyme>.</l>
      </lg>
      <lg id="s13" type="stanza">
        <l id="s13:l1" met="4" type="-+">Uwen Schiltknecht en wil ick <rhyme label="a" type="m">niet</rhyme></l>
        <l id="s13:l2" met="3" type="-+">Hy is my veel te <rhyme label="b" type="f">snoode</rhyme>,</l>
        <l id="s13:l3" met="4" type="-+">Al is mijn hooghen Berch ter <rhyme label="c" type="m">neder</rhyme></l>
        <l id="s13:l4" met="3" type="-+">Ick hoop ghy sult hem noch wel <rhyme label="b" type="f" corresp="#s13:l2">hooghen</rhyme>.</l>
      </lg>
      <lg id="s14" type="stanza">
        <l id="s14:l1" met="4" type="-+">Dat Meysken hadde een Broeder <rhyme label="a" type="m">stout</rhyme>,</l>
        <l id="s14:l2" met="3" type="-+">Hy was haer goet en <rhyme label="b" type="f">getrouwe</rhyme>,</l>
        <l id="s14:l3" met="4" type="-+">Als hy haer dede wel int <rhyme label="c" type="m">aenschijn</rhyme></l>
        <l id="s14:l4" met="3" type="-+">Hy beweest oock al metter <rhyme label="b" type="f" corresp="#s14:l2">trouwen</rhyme>.</l>
      </lg>
      <lg id="s15" type="stanza">
        <l id="s15:l1" met="4" type="-+">Och doen de Broeder ghewaere <rhyme label="a" type="m">wert</rhyme></l>
        <l id="s15:l2" met="3" type="-+">Dat sy een kindeken bleef <rhyme label="b" type="f">draghen</rhyme>,</l>
        <l id="s15:l3" met="4" type="-+">Hy ginck al voor den Ridder <rhyme label="c" type="m">staen</rhyme></l>
        <l id="s15:l4" met="3" type="-+">Hy badt hem mede om <rhyme label="b" type="f" corresp="#s15:l2">ghenaden</rhyme>.</l>
      </lg>
      <lg id="s16" type="stanza">
        <l id="s16:l1" met="4" type="-+">God groet u seyd' hy stout Ridder <rhyme label="a" type="m">vry</rhyme></l>
        <l id="s16:l2" met="3" type="-+">Stout Ridder vry van <rhyme label="b" type="f">waerden</rhyme>,</l>
        <l id="s16:l3" met="4" type="-+">Och die met uwen Kinde was <rhyme label="c" type="m">bevaen</rhyme></l>
        <l id="s16:l4" met="3" type="-+">Die leyt hier doot ter <rhyme label="b" type="f" corresp="#s16:l2">aerden</rhyme>.</l>
      </lg>
      <lg id="s17" type="stanza">
        <l id="s17:l1" met="4" type="-+">Och is sy doot dat schoone <rhyme label="a" type="m">Wijf</rhyme>,</l>
        <l id="s17:l2" met="3" type="-+">Die over schoone die ick <rhyme label="b" type="f">beminne</rhyme>,</l>
        <l id="s17:l3" met="4" type="-+">Soo en sal ick nu noch <rhyme label="c" type="m">nimmermeer</rhyme></l>
        <l id="s17:l4" met="3" type="-+">Mijn grauwen Ros <rhyme label="b" type="f" corresp="#s17:l2">berijden</rhyme>.</l>
      </lg>
      <lg id="s18" type="stanza">
        <l id="s18:l1" met="4" type="-+">Haelt mijn spere ende oock mijn <rhyme label="a" type="m">Schilt</rhyme></l>
        <l id="s18:l2" met="3" type="-+">Mijn Zweert al aen mijn <rhyme label="b" type="f">zijde</rhyme>,</l>
        <l id="s18:l3" met="4" type="-+">Ick wil gaen rijden selve <rhyme label="c" type="m">daer</rhyme></l>
        <l id="s18:l4" met="3" type="-+">Men vint der valsche bode <rhyme label="b" type="f" corresp="#s18:l2">veele</rhyme>.</l>
      </lg>
      <lg id="s19" type="stanza">
        <l id="s19:l1" met="4" type="-+">Och doen hy op der heyden <rhyme label="a" type="m">quam</rhyme></l>
        <l id="s19:l2" met="3" type="-+">Hy hoorde de Klocken <rhyme label="b" type="f">klincken</rhyme>,</l>
        <l id="s19:l3" met="4" type="-+">Hy hoorde wel aen der Klocken <rhyme label="c" type="m">klanck</rhyme></l>
        <l id="s19:l4" met="3" type="-+">Dat sy inder aerde moeste <rhyme label="b" type="f" corresp="#s19:l2">sincken</rhyme>.</l>
      </lg>
      <lg id="s20" type="stanza">
        <l id="s20:l1" met="4" type="-+">Hy nam zijnen bruynen <rhyme label="a" type="m">Schilt</rhyme></l>
        <l id="s20:l2" met="3" type="-+">Hy worp hem opter <rhyme label="b" type="f">aerden</rhyme>,</l>
        <l id="s20:l3" met="4" type="-+">Light daer light daer goet bruynen <rhyme label="c" type="m">Schilt</rhyme></l>
        <l id="s20:l4" met="3" type="-+">Van my en suldy niet ghedraghen <rhyme label="b" type="f" corresp="#s20:l2">werden</rhyme>.</l>
      </lg>
      <lg id="s21" type="stanza">
        <l id="s21:l1" met="4" type="-+">Heft op uwen bruynen <rhyme label="a" type="m">Schilt</rhyme></l>
        <l id="s21:l2" met="3" type="-+">Hanghet hem onder u <rhyme label="b" type="f">zijde</rhyme>,</l>
        <l id="s21:l3" met="4" type="-+">Al waer u Vader ende Moeder <rhyme label="c" type="m">doot</rhyme></l>
        <l id="s21:l4" met="3" type="-+">Den  rou moet ghy <rhyme label="b" type="f" corresp="#s21:l2">lijden</rhyme>.</l>
      </lg>
      <lg id="s22" type="stanza">
        <l id="s22:l1" met="4" type="-+">Al waer mijn Vader ende Moeder <rhyme label="a" type="m">doot</rhyme></l>
        <l id="s22:l2" met="3" type="-+">Ende mijn Broeders alle <rhyme label="b" type="f">vijve</rhyme>,</l>
        <l id="s22:l3" met="4" type="-+">Zoo en waer die rouwe niet alsoo <rhyme label="c" type="m">groot</rhyme></l>
        <l id="s22:l4" met="3" type="-+">Als hy is van dese schoone <rhyme label="b" type="f" corresp="#s22:l2">Wijve</rhyme>.</l>
      </lg>
      <lg id="s23" type="stanza">
        <l id="s23:l1" met="4" type="-+">Doen hy op dat Kerck-hof <rhyme label="a" type="m">quam</rhyme></l>
        <l id="s23:l2" met="3" type="-+">Hy hoorde die Papen <rhyme label="b" type="f">singhen</rhyme>,</l>
        <l id="s23:l3" met="4" type="-+">Hy hoorde wel ander Papen <rhyme label="c" type="m">sanck</rhyme></l>
        <l id="s23:l4" met="3" type="-+">Dat sy Vigilien <rhyme label="b" type="f" corresp="#s23:l2">songhen</rhyme>.</l>
      </lg>
      <lg id="s24" type="stanza">
        <l id="s24:l1" met="4" type="-+">Doen hy inde kercken <rhyme label="a" type="m">tradt</rhyme></l>
        <l id="s24:l2" met="3" type="-+">Hy sach sijn Liefste staen in de <rhyme label="b" type="f">bare</rhyme>,</l>
        <l id="s24:l3" met="4" type="-+">Gedeckt met een <rhyme label="c" type="m">baren-kleedt</rhyme></l>
        <l id="s24:l4" met="3" type="-+">Recht oft sy nu doot <rhyme label="b" type="f" corresp="#s24:l2">ware</rhyme>.</l>
      </lg>
      <lg id="s25" type="stanza">
        <l id="s25:l1" met="4" type="-+">Hy hief op dat <rhyme label="a" type="m">baren-kleedt</rhyme></l>
        <l id="s25:l2" met="3" type="-+">Hy sach haer kleyn Vingerken <rhyme label="b" type="f">roeren</rhyme>,</l>
        <l id="s25:l3" met="4" type="-+">Och doen loech haer rooden <rhyme label="c" type="m">mont</rhyme></l>
        <l id="s25:l4" met="3" type="-+">Doen sy den Ridder <rhyme label="b" type="f" corresp="#s25:l2">voelde</rhyme>.</l>
      </lg>
      <lg id="s26" type="stanza">
        <l id="s26:l1" met="4" type="-+">Staet op staet op mijn soete <rhyme label="a" type="m">Lief</rhyme></l>
        <l id="s26:l2" met="3" type="-+">Wel overschoone <rhyme label="b" type="f">Ionck-vrouwe</rhyme>,</l>
        <l id="s26:l3" met="4" type="-+">Ick en sal u nu noch <rhyme label="c" type="m">nimmermeer</rhyme></l>
        <l id="s26:l4" met="3" type="-+">Doen so grooten <rhyme label="b" type="f" corresp="#s26:l2">ontrouwe</rhyme>.</l>
      </lg>
      <lg id="s27" type="stanza">
        <l id="s27:l1" met="4" type="-+">Wel op wel op mijn soete <rhyme label="a" type="m">Lief</rhyme></l>
        <l id="s27:l2" met="3" type="-+">Mijn over schoone <rhyme label="b" type="f">Ionck-vrouwe</rhyme>,</l>
        <l id="s27:l3" met="4" type="-+">Al waert mijn Vader en Moeder <rhyme label="c" type="m">leet</rhyme>,</l>
        <l id="s27:l4" met="3" type="-+">Soo sal ick u tot eenen Wijve <rhyme label="b" type="f" corresp="#s27:l2">trouwen</rhyme>.</l>
      </lg>
      <lg id="s28" type="stanza">
        <l id="s28:l1" met="4" type="-+">Al waert mijn Vader ende Moeder <rhyme label="a" type="m">leet</rhyme>,</l>
        <l id="s28:l2" met="3" type="-+">Ende mijn Broeders alle <rhyme label="b" type="f">vyve</rhyme>,</l>
        <l id="s28:l3" met="4" type="-+">Soo sal ick u houden tot mijn <rhyme label="c" type="m">Bruyt</rhyme></l>
        <l id="s28:l4" met="3" type="-+">Ende trouwen tot een <rhyme label="b" type="f" corresp="#s28:l2">Wijve</rhyme>.</l>
      </lg>
    </lg>
  </text>
</song>
