<?xml version='1.0' encoding='utf-8' standalone='yes'?>
<song>
  <meta>
    <id>192518</id>
    <date>
      <year-start>1703</year-start>
      <year-end>1703</year-end>
    </date>
    <location>
      <orginal-name>amsterdam</orginal-name>
      <standard-name>Amsterdam, The Netherlands</standard-name>
      <coordinates>
        <lon>52.3745403</lon>
        <lat>4.89797550561798</lat>
      </coordinates>
    </location>
    <tags/>
    <melody/>
  <author>Anonymous</author></meta>
  <text>
    <lg type="song">
      <lg id="s1" type="stanza">
        <l id="s1:l1">Sa vereenigde Nederlanden,</l>
        <l id="s1:l2">Laet nu vry pick-tonnen branden,</l>
        <l id="s1:l3">Jn dees tijdt,</l>
        <l id="s1:l4">Jn dees tijdt,</l>
        <l id="s1:l5">Ter eeren van sijn Majesteyt,</l>
        <l id="s1:l6">Koning William van Brittanjen,</l>
        <l id="s1:l7">Onse Edel vorst van Oranjen,</l>
        <l id="s1:l8">Heeft gebraght,</l>
        <l id="s1:l9">Heeft gebraght,</l>
        <l id="s1:l10">'t Heel Yerlandt nu sijn macht.</l>
      </lg>
      <lg id="s2" type="stanza">
        <l id="s2:l1">Ons edel Oranje Bloeme,</l>
        <l id="s2:l2">Quam daer als een Leeuw vol roeme,</l>
        <l id="s2:l3">Jn Yerlant,</l>
        <l id="s2:l4">Jn Yerlandt,</l>
        <l id="s2:l5">Voor de oogen van onsen vyandt,</l>
        <l id="s2:l6">O ghy tweeden Alexander,</l>
        <l id="s2:l7">Ghy bent als een Salmander,</l>
        <l id="s2:l8">Niet vervaert,</l>
        <l id="s2:l9">Niet vervaert,</l>
        <l id="s2:l10">Voor geen vuur of voor geen zwaert.</l>
      </lg>
      <lg id="s3" type="stanza">
        <l id="s3:l1">Voor 't Hooft van u heel Armade,</l>
        <l id="s3:l2">Quaemt ghy William vol genade,</l>
        <l id="s3:l3">Jn Persoon,</l>
        <l id="s3:l4">Jn Persoon,</l>
        <l id="s3:l5">En riep met blijden toon,</l>
        <l id="s3:l6">Sa couragie mijn Hollanders,</l>
        <l id="s3:l7">Waegt u leven voor malkanders,</l>
        <l id="s3:l8">Want Yerlandt,</l>
        <l id="s3:l9">Want Yerlandt,</l>
        <l id="s3:l10">Moet nu komen in mijn handt.</l>
      </lg>
      <lg id="s4" type="stanza">
        <l id="s4:l1">Sa couragie nu als vroomen,</l>
        <l id="s4:l2">Tast nu vry toe sonder schroomen,</l>
        <l id="s4:l3">Wilt voortaen,</l>
        <l id="s4:l4">wilt voortaen,</l>
        <l id="s4:l5">Uwen Koningh trouw bystaen.</l>
        <l id="s4:l6">Sy sloegen vol ongenuchte,</l>
        <l id="s4:l7">Dat sy dreven op de vluchte,</l>
        <l id="s4:l8">Uyt het veld,</l>
        <l id="s4:l9">Uyt het veldt,</l>
        <l id="s4:l10">Jacob Stuwaert sijn gewelt.</l>
      </lg>
      <lg id="s5" type="stanza">
        <l id="s5:l1">Jacob Stuwaert was vol schromen,</l>
        <l id="s5:l2">Stracks heeft hy den vlucht genomen,</l>
        <l id="s5:l3">So hy sagh,</l>
        <l id="s5:l4">So hy sagh,</l>
        <l id="s5:l5">Dat verlooren was de slagh;</l>
        <l id="s5:l6">Och hy ginck hem stracks verbergen,</l>
        <l id="s5:l7">Al tusschen die hooge bergen,</l>
        <l id="s5:l8">'k Segh voorwaer,</l>
        <l id="s5:l9">'k Segh voorwaer,</l>
        <l id="s5:l10">Als een arme kluysenaer.</l>
      </lg>
      <lg id="s6" type="stanza">
        <l id="s6:l1">Soo haest als hy had vernomen,</l>
        <l id="s6:l2">Dat Dublin was overkomen,</l>
        <l id="s6:l3">Aen William,</l>
        <l id="s6:l4">Aen William,</l>
        <l id="s6:l5">Aen ons schoon Oranje stam,</l>
        <l id="s6:l6">So moest hy met groot hertseeren,</l>
        <l id="s6:l7">Wederom naer Vranckrijck keeren,</l>
        <l id="s6:l8">Om te plant,</l>
        <l id="s6:l9">om te plant,</l>
        <l id="s6:l10">Nieuwe wijngaert op het landt.</l>
      </lg>
      <lg id="s7" type="stanza">
        <l id="s7:l1">Wat sal ons Lodivicus dincken,</l>
        <l id="s7:l2">Dat Oranje nu gaet blincken,</l>
        <l id="s7:l3">Jn Yerlandt,</l>
        <l id="s7:l4">Jn Yerlandt,</l>
        <l id="s7:l5">En dat Stuwaert is van kant,</l>
        <l id="s7:l6">Williams vruchten soet van geure,</l>
        <l id="s7:l7">Ruyckt men de heele werelt deure,</l>
        <l id="s7:l8">'k Segh vol roem,</l>
        <l id="s7:l9">'k Segh vol roem,</l>
        <l id="s7:l10">d'Appels voor de Lelien Bloem.</l>
      </lg>
      <lg id="s8" type="stanza">
        <l id="s8:l1">Danckt nu de Hemelsch Vader</l>
        <l id="s8:l2">Menschen vry allegader,</l>
        <l id="s8:l3">t' Allen kant,</l>
        <l id="s8:l4">t'Allen kant,</l>
        <l id="s8:l5">Door ons gantsche Nederlandt,</l>
        <l id="s8:l6">Nu ghy siet d'Oranje stralen,</l>
        <l id="s8:l7">Overdeckt de Yersche palen,</l>
        <l id="s8:l8">Drinckt eens om,</l>
        <l id="s8:l9">Drinckt eens om,</l>
        <l id="s8:l10">Ter eeren van ons Orangjen Blom.</l>
      </lg>
    </lg>
  </text>
</song>
