<?xml version='1.0' encoding='utf-8' standalone='yes'?>
<song>
  <meta>
    <id>2540</id>
    <date>
      <year-start>1622</year-start>
      <year-end>1622</year-end>
    </date>
    <location>
      <orginal-name>amsterdam</orginal-name>
      <standard-name>Amsterdam, The Netherlands</standard-name>
      <coordinates>
        <lon>52.3745403</lon>
        <lat>4.89797550561798</lat>
      </coordinates>
    </location>
    <tags>
      <tag standard-name="klaaglied" translation="lamentation">klaaglied</tag>
    </tags>
    <melody>Ik wou dat ik was een wilde zwaan</melody>
    <categories>
      <category translation="emotions">emoties</category>
    </categories>
  <author>G.A. Bredero</author></meta>
  <text>
    <lg type="song">
      <lg id="s1" type="stanza">
        <l id="s1:l1" met="5" type="-+">Wat baat my den dranc daer ellick vreughd uyt <rhyme label="a" type="m">suygd</rhyme>?</l>
        <l id="s1:l2" met="5" type="-+">En dit lief gheselschap dat nu dus singht en <rhyme label="a" type="m" corresp="#s1:l1">juyghd</rhyme>,</l>
        <l id="s1:l3" met="3" type="-+">Met bly en soet <rhyme label="b" type="m">gelach</rhyme>?</l>
        <l id="s1:l4" met="4" type="-+">Als't oogh hier niet // de liefste <rhyme label="c" type="m">siet</rhyme>,</l>
        <l id="s1:l5" met="3" type="-+">Die ick so gaeren <rhyme label="b" type="m" corresp="#s1:l3">sach</rhyme>.</l>
      </lg>
      <lg id="s2" type="stanza">
        <l id="s2:l1" met="5" type="-+">Speelt ghy, en danst vry de lieve lange <rhyme label="a" type="m">nacht</rhyme>,</l>
        <l id="s2:l2" met="5" type="-+">Laet my myn selven vermaken met myn <rhyme label="a" type="m" corresp="#s2:l1">clacht</rhyme>,</l>
        <l id="s2:l3" met="3" type="-+">Die't hart uyt droefheyt <rhyme label="b" type="m">dicht</rhyme>:</l>
        <l id="s2:l4" met="4" type="-+">Ick sal in myn // smart vrolijc <rhyme label="c" type="m">syn</rhyme></l>
        <l id="s2:l5" met="3" type="-+">Of ten minsten wat <rhyme label="b" type="m" corresp="#s2:l3">verlicht</rhyme>.</l>
      </lg>
      <lg id="s3" type="stanza">
        <l id="s3:l1" met="5" type="-+">Ach! daer een ander gheluckich hem <rhyme label="a" type="m">bevindt</rhyme>,</l>
        <l id="s3:l2" met="5" type="-+">Nevens de gene die hy van herte <rhyme label="a" type="m" corresp="#s3:l1">mint</rhyme>,</l>
        <l id="s3:l3" met="3" type="-+">Daer sit ick hier <rhyme label="b" type="m">alleen</rhyme>:</l>
        <l id="s3:l4" met="4" type="-+">Diens groot gheluck // vermeert myn <rhyme label="c" type="m">druck</rhyme></l>
        <l id="s3:l5" met="3" type="-+">Met droeve <rhyme label="b" type="m" corresp="#s3:l3">treuriche'en</rhyme>.</l>
      </lg>
      <lg id="s4" type="stanza">
        <l id="s4:l1" met="5" type="-+">Niet dat ick yemant syn voorspoet hier <rhyme label="a" type="m">beny</rhyme>,</l>
        <l id="s4:l2" met="5" type="-+">Maer ick beklaegh het wreet geval, dat <rhyme label="a" type="m" corresp="#s4:l1">my</rhyme></l>
        <l id="s4:l3" met="3" type="-+">Dus dompelt in't <rhyme label="b" type="m">verdriet</rhyme>:</l>
        <l id="s4:l4" met="4" type="-+">Hierom ben ick // niet in myn <rhyme label="c" type="m">schick</rhyme>,</l>
        <l id="s4:l5" met="3" type="-+">So ghy hier merck'lijck <rhyme label="b" type="m" corresp="#s4:l3">siet</rhyme>,</l>
      </lg>
      <lg id="s5" type="stanza">
        <l id="s5:l1" met="5" type="-+">Gaet hene Speelnoot, verheucht de jonge <rhyme label="a" type="m">lien</rhyme>,</l>
        <l id="s5:l2" met="5" type="-+">Ick sal myn selven van binnen wat <rhyme label="a" type="m" corresp="#s5:l1">besien</rhyme>,</l>
        <l id="s5:l3" met="3" type="-+">En dromen van myn <rhyme label="b" type="m">Vrouw</rhyme>,</l>
        <l id="s5:l4" met="4" type="-+">Al ist bedroch // het sal my <rhyme label="c" type="m">noch</rhyme></l>
        <l id="s5:l5" met="3" type="-+">Verquicken in myn <rhyme label="b" type="m" corresp="#s5:l3">rouw</rhyme>.</l>
      </lg>
      <lg id="s6" type="stanza">
        <l id="s6:l1" met="5" type="-+">Gaet hene, gaet hene, wat hebdy noch al <rhyme label="a" type="m">praets</rhyme>,</l>
        <l id="s6:l2" met="5" type="-+">Misschien sal u een ander afwinnen nu de <rhyme label="a" type="m" corresp="#s6:l1">plaets</rhyme>,</l>
        <l id="s6:l3" met="3" type="-+">En't Meysjen oock daer <rhyme label="b" type="m">by</rhyme>:</l>
        <l id="s6:l4" met="4" type="-+">Ick danck u seer // van al de <rhyme label="c" type="m">Eer</rhyme>,</l>
        <l id="s6:l5" met="3" type="-+">Die ghy bewijst aen <rhyme label="b" type="m" corresp="#s6:l3">my</rhyme>.</l>
      </lg>
      <lg id="s7" type="stanza">
        <l id="s7:l1" met="5" type="-+">Helaes Princesje! helaes waer sydy <rhyme label="a" type="m">nu</rhyme>?</l>
        <l id="s7:l2" met="5" type="-+">Helaes myn leven! wat ben ick sonder <rhyme label="a" type="m" corresp="#s7:l1">u</rhyme>?</l>
        <l id="s7:l3" met="3" type="-+">Een schaduw' en een <rhyme label="b" type="m">schijn</rhyme>,</l>
        <l id="s7:l4" met="4" type="-+">En geen ding min // als die ick <rhyme label="c" type="m">bin</rhyme>,</l>
        <l id="s7:l5" met="3" type="-+">Als ick by u mach <rhyme label="b" type="m" corresp="#s7:l3">zijn</rhyme>.</l>
      </lg>
    </lg>
  </text>
</song>
