<?xml version='1.0' encoding='utf-8' standalone='yes'?>
<song>
  <meta>
    <id>34090</id>
    <date>
      <year-start>1660</year-start>
      <year-end>1660</year-end>
    </date>
    <location>
      <orginal-name>brussel</orginal-name>
      <standard-name>Brussels, Belgium</standard-name>
      <coordinates>
        <lon>50.8465573</lon>
        <lat>4.351697</lat>
      </coordinates>
    </location>
    <tags>
      <tag standard-name="vermaanlied" translation="admonitory song">vermaanlied</tag>
    </tags>
    <melody>Toen Daphne de overschone maagd</melody>
    <categories>
      <category translation="religion">godsdienst</category>
    </categories>
  <author>Peeter de Vleeschoudere</author></meta>
  <text>
    <lg type="song">
      <lg id="s1" type="stanza">
        <l id="s1:l1" met="4" type="-+">MEnsch, die de wereld seer <rhyme label="a" type="m">be-mint</rhyme>,</l>
        <l id="s1:l2" met="4" type="-+">Let wel op uw' ganghen, waer henen ghy <rhyme label="b" type="m">daelt</rhyme>;</l>
        <l id="s1:l3" met="4" type="-+">Het dient in ernst te zyn <rhyme label="a" type="m" corresp="#s1:l1">ver-sint</rhyme>;</l>
        <l id="s1:l4" met="4" type="-+">Die 's werelds wegh in gaet, hy lichtelyck <rhyme label="b" type="m" corresp="#s1:l2">faelt</rhyme>:</l>
        <l id="s1:l5" met="4" type="+-">Wilt nemen acht op dese <rhyme label="c" type="f">saecken</rhyme>,</l>
        <l id="s1:l6" met="4" type="+-">Dat's werelds wel-lust de menschen <rhyme label="d" type="m">be-drieght</rhyme>;</l>
        <l id="s1:l7" met="4" type="+-">Dat Christus stirf, om u saeligh te <rhyme label="c" type="f" corresp="#s1:l5">maecken</rhyme>;</l>
        <l id="s1:l8" met="4" type="+-">Dat ghy oock moet sterven, daer 't al <rhyme label="d" type="m" corresp="#s1:l6">aen-lieght</rhyme>;</l>
        <l id="s1:l9" met="3" type="-+">Dat all' de <rhyme label="e" type="m">eeuwigheydt</rhyme></l>
        <l id="s1:l10" met="3" type="-+">Aen eens te sterven <rhyme label="e" type="m" corresp="#s1:l9">leyt</rhyme>.</l>
        <l id="s1:l11" met="4" type="+-">Een goey dood volght het eeuwigh <rhyme label="f" type="m">gheluck</rhyme>,</l>
        <l id="s1:l12" met="4" type="-+">Die sterft in dood-sonde, kryght eeuwighen <rhyme label="f" type="m" corresp="#s1:l11">druck</rhyme>.</l>
      </lg>
      <lg id="s2" type="stanza">
        <l id="s2:l1" met="4" type="-+">Waer't dat ghy wist, dat uwen <rhyme label="a" type="m">tyd</rhyme></l>
        <l id="s2:l2" met="4" type="-+">Uws levens sou dueren alleenlyck een <rhyme label="b" type="m">maend</rhyme>;</l>
        <l id="s2:l3" met="4" type="-+">Gh'en soud noyt konnen zyn <rhyme label="a" type="m" corresp="#s2:l1">ver-blydt</rhyme>,</l>
        <l id="s2:l4" met="4" type="-+">Uw aen-schyn sou leken van droefheyd <rhyme label="b" type="m" corresp="#s2:l2">be-traend</rhyme>.</l>
        <l id="s2:l5" met="4" type="+-">Hoe kont ghy dan soo vrolyck <rhyme label="c" type="f">wesen</rhyme>,</l>
        <l id="s2:l6" met="4" type="+-">Daer niet een urken ghy seker en <rhyme label="d" type="m">zyt</rhyme>?</l>
        <l id="s2:l7" met="4" type="+-">Daer misschien, noch eer de sonn' is <rhyme label="c" type="f" corresp="#s2:l5">gheresen</rhyme>,</l>
        <l id="s2:l8" met="4" type="+-">De dood u sal aen-doen den droeven <rhyme label="d" type="m" corresp="#s2:l6">strydt</rhyme>?</l>
        <l id="s2:l9" met="3" type="-+">Des werelds blydschap <rhyme label="e" type="m">al</rhyme></l>
        <l id="s2:l10" met="3" type="-+">U dan niet helpen <rhyme label="e" type="m" corresp="#s2:l9">sal</rhyme>;</l>
        <l id="s2:l11" met="4" type="+-">Peyst op de dood, en let op uw <rhyme label="f" type="m">end</rhyme>;</l>
        <l id="s2:l12" met="4" type="-+">Naer 't eynde sal volghen de vreughd, oft <rhyme label="f" type="m" corresp="#s2:l11">ellend</rhyme>.</l>
      </lg>
      <lg id="s3" type="stanza">
        <l id="s3:l1" met="4" type="-+">Al sier ghy duysend sondaers <rhyme label="a" type="m">vry</rhyme></l>
        <l id="s3:l2" met="4" type="-+">Des werelds ghenoeghten hand-teren met <rhyme label="b" type="m">vreughdt</rhyme>;</l>
        <l id="s3:l3" met="4" type="-+">Laet u niet voor-staen, dat oock <rhyme label="a" type="m" corresp="#s3:l1">ghy</rhyme></l>
        <l id="s3:l4" met="4" type="-+">Uw' lusten soo volghen, en sondighen <rhyme label="b" type="m" corresp="#s3:l2">meught</rhyme>.</l>
        <l id="s3:l5" met="4" type="+-">Alsser duysend vaeren ter <rhyme label="c" type="f">helle</rhyme>,</l>
        <l id="s3:l6" met="4" type="+-">Die on-ghebonden, heel gode-loos <rhyme label="d" type="m">zyn</rhyme>,</l>
        <l id="s3:l7" met="4" type="+-">Soud ghy dan willen zyn <rhyme label="c" type="f" corresp="#s3:l5">mede-gheselle</rhyme>,</l>
        <l id="s3:l8" met="4" type="+-">Om met hun te branden in d'helsche <rhyme label="d" type="m" corresp="#s3:l6">pyn</rhyme>?</l>
        <l id="s3:l9" met="3" type="-+">Van duysend word <rhyme label="e" type="m">ghedaen</rhyme>,</l>
        <l id="s3:l10" met="3" type="-+">Dat ghy noyt sult <rhyme label="e" type="m" corresp="#s3:l9">her-gaen</rhyme>;</l>
        <l id="s3:l11" met="4" type="+-">Maer sterven misschien met d'eersten <rhyme label="f" type="m">keer</rhyme>.</l>
        <l id="s3:l12" met="4" type="-+">Dus wacht u van sonde, en vreest God den <rhyme label="f" type="m" corresp="#s3:l11">Heer</rhyme>.</l>
      </lg>
      <lg id="s4" type="stanza">
        <l id="s4:l1" met="4" type="-+">Als ghy gheleeft hebt honderd <rhyme label="a" type="m">jaer</rhyme></l>
        <l id="s4:l2" met="4" type="-+">In voor-spoed, in ryckdom, in alle <rhyme label="b" type="m">wel-lust</rhyme>,</l>
        <l id="s4:l3" met="4" type="-+">Wat sal 't doch wesen al te <rhyme label="a" type="m" corresp="#s4:l1">gaer</rhyme>,</l>
        <l id="s4:l4" met="4" type="-+">Als ghy uw' ghesmtheyd sult hebben <rhyme label="b" type="m" corresp="#s4:l2">gheblust</rhyme>?</l>
        <l id="s4:l5" met="4" type="+-">Als all' dees' jaeren zyn <rhyme label="c" type="f">ver-schenen</rhyme>;</l>
        <l id="s4:l6" met="4" type="+-">En als u den lesten ooghen-blick <rhyme label="d" type="m">naeckt</rhyme>,</l>
        <l id="s4:l7" met="4" type="+-">Dat ghy af-lyvigh ver-trecken moet <rhyme label="c" type="f" corresp="#s4:l5">henen</rhyme>,</l>
        <l id="s4:l8" met="4" type="+-">En dat uw' lichaem in d'aerde <rhyme label="d" type="m" corresp="#s4:l6">gheraeckt</rhyme>?</l>
        <l id="s4:l9" met="3" type="-+">Daer light het lichaem <rhyme label="e" type="m">wel</rhyme>;</l>
        <l id="s4:l10" met="3" type="-+">Gaet uw' siel in de <rhyme label="e" type="m" corresp="#s4:l9">hell'</rhyme>,</l>
        <l id="s4:l11" met="4" type="+-">Wat sal u helpen all' 's werelds <rhyme label="f" type="m">goedt</rhyme>,</l>
        <l id="s4:l12" met="4" type="-+">Als uvve siel branden in 't eeuwigh vier <rhyme label="f" type="m" corresp="#s4:l11">moet</rhyme>?</l>
      </lg>
      <lg id="s5" type="stanza">
        <l id="s5:l1" met="4" type="-+">Stelt dan in vvoord, vverck, en <rhyme label="a" type="m">ghedacht</rhyme></l>
        <l id="s5:l2" met="4" type="-+">De dood, en het oordeel, den hemel, en <rhyme label="b" type="m">hell'</rhyme>,</l>
        <l id="s5:l3" met="4" type="-+">Het lyden Christi weerd <rhyme label="a" type="m" corresp="#s5:l1">ghe-acht</rhyme>,</l>
        <l id="s5:l4" met="4" type="-+">Des werelds wel-lust, die keert in <rhyme label="b" type="m" corresp="#s5:l2">ghequel</rhyme>,</l>
        <l id="s5:l5" met="4" type="+-">Dagh en nacht u al-tyd voor <rhyme label="c" type="f">ooghen</rhyme>,</l>
        <l id="s5:l6" met="4" type="+-">Als u den vyand tot sonde <rhyme label="d" type="m">bekoort</rhyme>,</l>
        <l id="s5:l7" met="4" type="+-">En syn in-ghevingh' en vvilt niet <rhyme label="c" type="f" corresp="#s5:l5">ghedooghen</rhyme>;</l>
        <l id="s5:l8" met="4" type="+-">Op dat gh' in den af-grond niet en <rhyme label="d" type="m" corresp="#s5:l6">ver-smoort</rhyme>;</l>
        <l id="s5:l9" met="3" type="-+">Maer peyst dat <rhyme label="e" type="m">d'eeuwigheyd</rhyme>,</l>
        <l id="s5:l10" met="3" type="-+">Aen dees' victori <rhyme label="e" type="m" corresp="#s5:l9">leyd</rhyme>.</l>
        <l id="s5:l11" met="4" type="+-">Wilt sonde vliên, aen-kleven de <rhyme label="f" type="m">deughd</rhyme>;</l>
        <l id="s5:l12" met="4" type="-+">Soo sult ghy eens komen in d'Hemelsche <rhyme label="f" type="m" corresp="#s5:l11">vreughd</rhyme>.</l>
      </lg>
    </lg>
  </text>
</song>
