<?xml version='1.0' encoding='utf-8' standalone='yes'?>
<song>
  <meta>
    <id>35679</id>
    <date>
      <year-start>1659</year-start>
      <year-end>1659</year-end>
    </date>
    <location>
      <orginal-name>antwerpen</orginal-name>
      <standard-name>Antwerp, Belgium</standard-name>
      <coordinates>
        <lon>51.2211097</lon>
        <lat>4.3997081</lat>
      </coordinates>
    </location>
    <tags>
      <tag standard-name="heiligenlied" translation="saint song">heiligenlied</tag>
    </tags>
    <melody>Wilhelmus</melody>
    <categories>
      <category translation="religion">godsdienst</category>
    </categories>
  <author>Albertus Buitendyck</author></meta>
  <text>
    <lg type="song">
      <lg id="s1" type="stanza">
        <l id="s1:l1" met="3" type="-+">DE vroomheyt wordt <rhyme label="a" type="f">gepresen</rhyme></l>
        <l id="s1:l2" met="3" type="-+">Van de seer stercke <rhyme label="b" type="m">Leeuw</rhyme>;</l>
        <l id="s1:l3" met="3" type="-+">Hy vlucht nochtans door <rhyme label="a" type="f" corresp="#s1:l1">vreese</rhyme>,</l>
        <l id="s1:l4" met="3" type="-+">Als een Haen maeckt <rhyme label="b" type="m" corresp="#s1:l2">geschreeuw</rhyme>.</l>
        <l id="s1:l5" met="3" type="-+">Niet Emerens kost <rhyme label="c" type="f">scheyden</rhyme></l>
        <l id="s1:l6" met="3" type="-+">Van Godt of Sint <rhyme label="d" type="m">Agniet</rhyme>,</l>
        <l id="s1:l7" met="3" type="-+">Wat pijn men haer <rhyme label="c" type="f" corresp="#s1:l5">voor-leyden</rhyme></l>
        <l id="s1:l8" met="3" type="-+">Sy was geen buygent <rhyme label="d" type="m" corresp="#s1:l6">Riet</rhyme></l>
      </lg>
      <lg id="s2" type="stanza">
        <l id="s2:l1" met="3" type="-+">Ey! vroome <rhyme label="a" type="f">Catholijcken</rhyme>,</l>
        <l id="s2:l2" met="3" type="-+">Wilt van het Roomsch <rhyme label="b" type="m">Geloof</rhyme>,</l>
        <l id="s2:l3" met="3" type="-+">Om goedt, noch doodt <rhyme label="a" type="f" corresp="#s2:l1">beswijcken</rhyme>.</l>
        <l id="s2:l4" met="3" type="-+">Seght nu, ick dat <rhyme label="b" type="m" corresp="#s2:l2">beloof</rhyme>;</l>
        <l id="s2:l5" met="3" type="-+">Boven al Godt wilt <rhyme label="c" type="f">achten</rhyme>;</l>
        <l id="s2:l6" met="3" type="-+">Leeft na Godts wil en <rhyme label="d" type="m">wensch</rhyme>,</l>
        <l id="s2:l7" met="3" type="-+">U loon staet te <rhyme label="c" type="f" corresp="#s2:l5">verwachten</rhyme></l>
        <l id="s2:l8" met="3" type="-+">By uwen <rhyme label="d" type="m" corresp="#s2:l6">Emerens</rhyme>.</l>
      </lg>
      <lg id="s3" type="stanza">
        <l id="s3:l1" met="3" type="-+">Ghy lof, en eer der <rhyme label="a" type="f">Vrouwen</rhyme>,</l>
        <l id="s3:l2" met="3" type="-+">Ons <rhyme label="b" type="m">Emerentiaen</rhyme>!</l>
        <l id="s3:l3" met="3" type="-+">Op onse druck en <rhyme label="a" type="f" corresp="#s3:l1">rouwen</rhyme>,</l>
        <l id="s3:l4" met="3" type="-+">Wilt uwe oogen <rhyme label="b" type="m" corresp="#s3:l2">slaen</rhyme>:</l>
        <l id="s3:l5" met="3" type="-+">En als wy moeten <rhyme label="c" type="f">sterven</rhyme></l>
        <l id="s3:l6" met="3" type="-+">Versoeckt van Godes <rhyme label="d" type="m">Soon</rhyme>,</l>
        <l id="s3:l7" met="3" type="-+">Dat wy alle <rhyme label="c" type="f" corresp="#s3:l5">verwerven</rhyme></l>
        <l id="s3:l8" met="3" type="-+">Blijtschap in 's Hemels <rhyme label="d" type="m" corresp="#s3:l6">throon</rhyme>.</l>
      </lg>
      <lg id="s4" type="stanza">
        <l id="s4:l1" met="3" type="-+">Stort Iesu, dese <rhyme label="a" type="f">gaven</rhyme></l>
        <l id="s4:l2" met="3" type="-+">Uyt uwe milden <rhyme label="b" type="m">handt</rhyme>,</l>
        <l id="s4:l3" met="3" type="-+">Aen ons, die sijne <rhyme label="a" type="f" corresp="#s4:l1">Slaven</rhyme></l>
        <l id="s4:l4" met="3" type="-+">Van uw', hier in dit <rhyme label="b" type="m" corresp="#s4:l2">landt</rhyme>.</l>
        <l id="s4:l5" met="3" type="-+">En geeft uwe <rhyme label="c" type="f">Dienst-maeghden</rhyme></l>
        <l id="s4:l6" met="3" type="-+">Die hier ter Lande <rhyme label="d" type="m">zijn</rhyme>,</l>
        <l id="s4:l7" met="3" type="-+">Uw' oprecht te <rhyme label="c" type="f" corresp="#s4:l5">behagen</rhyme></l>
        <l id="s4:l8" met="3" type="-+">Sonder bedrogh, of <rhyme label="d" type="m" corresp="#s4:l6">schijn</rhyme>.</l>
      </lg>
      <lg id="s5" type="stanza">
        <l id="s5:l1" met="3" type="-+">Ey! Iesu houdt noch <rhyme label="a" type="f">open</rhyme>,</l>
        <l id="s5:l2" met="3" type="-+">En sluyt niet uwen <rhyme label="b" type="m">handt</rhyme>;</l>
        <l id="s5:l3" met="3" type="-+">Geeft ons daer wy na <rhyme label="a" type="f" corresp="#s5:l1">hoopen</rhyme></l>
        <l id="s5:l4" met="3" type="-+">U Hemels <rhyme label="b" type="m" corresp="#s5:l2">Vaderlandt</rhyme>.</l>
        <l id="s5:l5" met="3" type="-+">Ey! wilt ons alle <rhyme label="c" type="f">leyden</rhyme></l>
        <l id="s5:l6" met="3" type="-+">Daer na in 's Hemels <rhyme label="d" type="m">vreught</rhyme>,</l>
        <l id="s5:l7" met="3" type="-+">Als wy van hier <rhyme label="c" type="f" corresp="#s5:l5">verscheyden</rhyme>,</l>
        <l id="s5:l8" met="3" type="-+">Maeckt ons hier door <rhyme label="d" type="m" corresp="#s5:l6">verheught</rhyme>.</l>
      </lg>
    </lg>
  </text>
</song>
